Flip flops/tff.v
module tff(t,clk,reset,q);
input t, clk, reset;
output q;
reg q;

always@(posedge clk or posedge reset)
begin
	if(reset)
 		q <= 1'b0;
	else if(t==1)
		q <= !q;
	else
		q <= q;
end
endmodule

Flip flops/tff_tb.v
`include "tff.v"

module tff_tb;
reg t, clk, reset;
wire q;

initial
	begin
$dumpfile("tff_tb.vcd");
$dumpvars(0,tff_tb);
end

tff t1(t, clk, reset, q);


initial
begin
reset=0;
clk =0;
t=0;
end

always 
#5  clk =  ! clk; 

  always #10 t=~t;		//after 10sec d value is changing
/*
initial
begin
#5 reset =1'b0;
d=0;
#5 d = 1'b1;

end
*/

always@(posedge clk or posedge reset)
	begin
 		$display("t=%b, clk=%b, rst=%b,q=%b\n", t, clk, reset, q);
	end 

initial

	#50 $finish;
endmodule

Flip flops/tff_tb.vcd
$date
	Wed Aug 14 10:32:23 2019
$end
$version
	Icarus Verilog
$end
$timescale
	1s
$end
$scope module tff_tb $end
$var wire 1 ! q $end
$var reg 1 " clk $end
$var reg 1 # reset $end
$var reg 1 $ t $end
$scope module t1 $end
$var wire 1 % clk $end
$var wire 1 & reset $end
$var wire 1 ' t $end
$var reg 1 ( q $end
$upscope $end
$upscope $end
$enddefinitions $end
#0
$dumpvars
x(
0'
0&
0%
0$
0#
0"
x!
$end
#5
1(
1!
1"
1%
#10
0"
0%
1$
1'
#15
0(
0!
1"
1%
#20
0"
0%
0$
0'
#25
1(
1!
1"
1%
#30
0"
0%
1$
1'
#35
0(
0!
1"
1%
#40
0"
0%
0$
0'
#45
1(
1!
1"
1%
#50
0"
0%
1$
1'
