Registers/DFF.v
module D_FF(q,d,clk,reset);
output reg q;
input d,clk,reset;

always@(posedge clk)
begin
	if(reset==1'b1)
		q<=1'b0;
	
	else
		q<=d;
end	

endmodule

Registers/mux_4_1.v
module mux_4_1(y,s1,s0,i3,i2,i1,i0);

output reg y;
input i3,i2,i1,i0;
input s1,s0;

always@(s1,s0,i3,i2,i1,i0)
begin
	if(s0==0 & s1==0)
		y = i0;
		
	else if(s0==0 & s1==1)
		y = i1;
		
	if(s0==1 & s1==0)
		y = i2;
		
	if(s0==1 & s1==1)
		y = i3;
end

endmodule

Registers/USR.v
`include "DFF.v"
`include "mux_4_1.v"
module USR(O,I,clk,reset,s,SINR,SINL);
wire [3:0] w;
input [3:0] I;
input [1:0] s;
input clk;
input reset,SINR,SINL;
output [3:0] O;

	mux_4_1 m1(w[0],s[1],s[0],I[0],SINL,O[1],O[0]);
	mux_4_1 m2(w[1],s[1],s[0],I[1],O[0],O[2],O[1]);
	mux_4_1 m3(w[2],s[1],s[0],I[2],O[1],O[3],O[2]);
	mux_4_1 m4(w[3],s[1],s[0],I[3],O[2],SINR,O[3]);
	
	D_FF d1(O[0],w[0],clk,reset);
	D_FF d2(O[1],w[1],clk,reset);
	D_FF d3(O[2],w[2],clk,reset);
	D_FF d4(O[3],w[3],clk,reset);
	
endmodule

Registers/USR_tb.v
`include "USR.v"

module USR_tb;

//inputs

reg [3:0] I;
reg [1:0] s;
reg clk;
reg reset,SINR,SINL;

//outputs
wire [3:0] O;

initial
	begin
$dumpfile("USR_tb.vcd");
$dumpvars(0,USR_tb);
end

USR u(O,I,clk,reset,s,SINR,SINL);

initial
begin
reset=0;
clk =0;
//Din_left=1;	//Din = 1;
//SINR=1;
SINL =1;

s[1] = 0;	//shift left by 1
s[0] = 1;

#50
SINR =0;	  //shift right with zero
s[1] = 1;
s[0] = 0;

#50
s[1] = 1;		//parallel loading
s[0] = 1;
I = 4'b1111;

#50
s[1] = 0;		//no change
s[0] = 0;

end

always 
#5  clk =  ! clk; 
	


/*
initial
begin
#5 reset =1'b0;
d=0;
#5 d = 1'b1;

end
*/

always@(posedge clk)
	begin
 		$display($time, " S1 = %b, S0 = %b,  clk=%b, rst=%b, O=%b\n", s[1],s[0], clk, reset, O);
	end 

initial

	#200 $finish;
endmodule

Registers/USR_tb.vcd
$date
	Wed Aug 21 09:22:15 2019
$end
$version
	Icarus Verilog
$end
$timescale
	1s
$end
$scope module USR_tb $end
$var wire 4 ! O [3:0] $end
$var reg 4 " I [3:0] $end
$var reg 1 # SINL $end
$var reg 1 $ SINR $end
$var reg 1 % clk $end
$var reg 1 & reset $end
$var reg 2 ' s [1:0] $end
$scope module u $end
$var wire 4 ( I [3:0] $end
$var wire 1 # SINL $end
$var wire 1 $ SINR $end
$var wire 1 % clk $end
$var wire 1 & reset $end
$var wire 2 ) s [1:0] $end
$var wire 4 * w [3:0] $end
$var wire 4 + O [3:0] $end
$scope module d1 $end
$var wire 1 % clk $end
$var wire 1 , d $end
$var wire 1 & reset $end
$var reg 1 - q $end
$upscope $end
$scope module d2 $end
$var wire 1 % clk $end
$var wire 1 . d $end
$var wire 1 & reset $end
$var reg 1 / q $end
$upscope $end
$scope module d3 $end
$var wire 1 % clk $end
$var wire 1 0 d $end
$var wire 1 & reset $end
$var reg 1 1 q $end
$upscope $end
$scope module d4 $end
$var wire 1 % clk $end
$var wire 1 2 d $end
$var wire 1 & reset $end
$var reg 1 3 q $end
$upscope $end
$scope module m1 $end
$var wire 1 4 i0 $end
$var wire 1 5 i1 $end
$var wire 1 # i2 $end
$var wire 1 6 i3 $end
$var wire 1 7 s0 $end
$var wire 1 8 s1 $end
$var reg 1 9 y $end
$upscope $end
$scope module m2 $end
$var wire 1 : i0 $end
$var wire 1 ; i1 $end
$var wire 1 < i2 $end
$var wire 1 = i3 $end
$var wire 1 > s0 $end
$var wire 1 ? s1 $end
$var reg 1 @ y $end
$upscope $end
$scope module m3 $end
$var wire 1 A i0 $end
$var wire 1 B i1 $end
$var wire 1 C i2 $end
$var wire 1 D i3 $end
$var wire 1 E s0 $end
$var wire 1 F s1 $end
$var reg 1 G y $end
$upscope $end
$scope module m4 $end
$var wire 1 H i0 $end
$var wire 1 $ i1 $end
$var wire 1 I i2 $end
$var wire 1 J i3 $end
$var wire 1 K s0 $end
$var wire 1 L s1 $end
$var reg 1 M y $end
$upscope $end
$upscope $end
$upscope $end
$enddefinitions $end
#0
$dumpvars
xM
0L
1K
xJ
xI
xH
xG
0F
1E
xD
xC
xB
xA
x@
0?
1>
x=
x<
x;
x:
19
08
17
x6
x5
x4
x3
x2
x1
x0
x/
x.
x-
1,
bx +
bx1 *
b1 )
bx (
b1 '
0&
0%
x$
1#
bx "
bx !
$end
#5
1.
bx11 *
1@
1<
14
bx1 !
bx1 +
1-
1%
#10
0%
#15
10
bx111 *
1G
1C
1:
15
bx11 !
bx11 +
1/
1%
#20
0%
#25
12
b1111 *
1M
1I
1A
1;
bx111 !
bx111 +
11
1%
#30
0%
#35
1H
1B
b1111 !
b1111 +
13
1%
#40
0%
#45
1%
#50
02
b111 *
0M
07
0>
0E
0K
18
1?
1F
1L
0%
b10 '
b10 )
0$
#55
00
b11 *
0G
0H
0B
b111 !
b111 +
03
1%
#60
0%
#65
0.
b1 *
0@
0I
0A
0;
b11 !
b11 +
01
1%
#70
0%
#75
0,
b0 *
09
0C
0:
05
b1 !
b1 +
0/
1%
#80
0%
#85
0<
04
b0 !
b0 +
0-
1%
#90
0%
#95
1%
#100
1,
1.
10
12
19
1@
1G
b1111 *
1M
16
1=
1D
1J
17
1>
1E
1K
0%
b1111 "
b1111 (
b11 '
b11 )
#105
1<
14
1C
1:
15
1I
1A
1;
1H
1B
1-
1/
11
b1111 !
b1111 +
13
1%
#110
0%
#115
1%
#120
0%
#125
1%
#130
0%
#135
1%
#140
0%
#145
1%
#150
07
0>
0E
0K
08
0?
0F
0L
0%
b0 '
b0 )
